benerator_cumberpy/__init__.py
benerator_cumberpy/data/first-names.txt
benerator_cumberpy/data/last-names.txt
benerator_cumberpy-0.2.3.dist-info/LICENSE.txt
benerator_cumberpy-0.2.3.dist-info/METADATA
benerator_cumberpy-0.2.3.dist-info/WHEEL
benerator_cumberpy-0.2.3.dist-info/entry_points.txt
benerator_cumberpy-0.2.3.dist-info/top_level.txt
benerator_cumberpy-0.2.3.dist-info/RECORD
