Metadata-Version: 2.1
Name: benerator-cumberpy
Version: 0.2.3
Summary: A Ben Cumberbatch-like name generator
Home-page: https://github.com/fdmarcin/benerator-cumberpy
Author: Marcin Sędłak-Jakubowski
Author-email: fdmarcin@gmail.com
License: MIT
Download-URL: https://github.com/fdmarcin/benerator-cumberpy/archive/0.2.3.tar.gz
Keywords: benedict cumberbatch word generator
Platform: UNKNOWN
Classifier: Development Status :: 4 - Beta
Classifier: Environment :: Console
Classifier: Intended Audience :: End Users/Desktop
Classifier: Topic :: Games/Entertainment
Classifier: License :: OSI Approved :: MIT License
Classifier: Programming Language :: Python :: 3
Classifier: Programming Language :: Python :: 3.3
Classifier: Programming Language :: Python :: 3.4
Classifier: Programming Language :: Python :: 3.5
Classifier: Programming Language :: Python :: 3.6
Classifier: Programming Language :: Python :: 3.7
Classifier: Programming Language :: Python :: 3.8
Classifier: Programming Language :: Python :: 3.9
